odoo/addons/website_video_preview/README.rst
odoo/addons/website_video_preview/__init__.py
odoo/addons/website_video_preview/__manifest__.py
odoo/addons/website_video_preview/i18n/website_video_preview.pot
odoo/addons/website_video_preview/readme/CONTRIBUTORS.rst
odoo/addons/website_video_preview/readme/DESCRIPTION.rst
odoo/addons/website_video_preview/readme/ROADMAP.rst
odoo/addons/website_video_preview/readme/USAGE.rst
odoo/addons/website_video_preview/static/description/icon.png
odoo/addons/website_video_preview/static/description/index.html
odoo/addons/website_video_preview/static/src/img/yt_button.png
odoo/addons/website_video_preview/static/src/js/website_video_preview.editor.js
odoo/addons/website_video_preview/static/src/js/website_video_preview.frontend.js
odoo/addons/website_video_preview/static/src/less/website_video_preview.less
odoo/addons/website_video_preview/templates/assets.xml
odoo11_addon_website_video_preview-11.0.1.0.0.99.dev12.dist-info/METADATA
odoo11_addon_website_video_preview-11.0.1.0.0.99.dev12.dist-info/WHEEL
odoo11_addon_website_video_preview-11.0.1.0.0.99.dev12.dist-info/top_level.txt
odoo11_addon_website_video_preview-11.0.1.0.0.99.dev12.dist-info/RECORD
